{
	"客场球队":{
		"球队名称":"呼和浩特中优",
		"防守热区":{
			"1":"0.0%",
			"2":"1.52%",
			"3":"1.52%",
			"4":"9.09%",
			"5":"1.52%",
			"6":"3.03%",
			"7":"0.0%",
			"8":"0.0%",
			"9":"0.0%",
			"10":"6.06%",
			"11":"18.18%",
			"12":"16.67%",
			"13":"0.0%",
			"14":"0.0%",
			"15":"1.52%",
			"16":"4.55%",
			"17":"7.58%",
			"18":"10.61%",
			"19":"0.0%",
			"20":"1.52%",
			"21":"4.55%",
			"22":"7.58%",
			"23":"3.03%",
			"24":"1.52%"
		},
		"进攻热区":{
			"1":"23.64%",
			"2":"18.18%",
			"3":"3.64%",
			"4":"5.45%",
			"5":"1.82%",
			"6":"1.82%",
			"7":"1.82%",
			"8":"1.82%",
			"9":"3.64%",
			"10":"5.45%",
			"11":"5.45%",
			"12":"0.0%",
			"13":"0.0%",
			"14":"0.0%",
			"15":"0.0%",
			"16":"1.82%",
			"17":"1.82%",
			"18":"1.82%",
			"19":"7.27%",
			"20":"9.09%",
			"21":"5.45%",
			"22":"0.0%",
			"23":"0.0%",
			"24":"0.0%"
		},
		"综合热区":{
			"1":"2.9%",
			"2":"5.56%",
			"3":"4.83%",
			"4":"7.0%",
			"5":"2.9%",
			"6":"2.42%",
			"7":"0.72%",
			"8":"1.69%",
			"9":"3.38%",
			"10":"6.76%",
			"11":"7.73%",
			"12":"5.31%",
			"13":"1.21%",
			"14":"2.17%",
			"15":"2.66%",
			"16":"7.25%",
			"17":"3.62%",
			"18":"6.28%",
			"19":"1.45%",
			"20":"5.56%",
			"21":"5.56%",
			"22":"9.42%",
			"23":"2.9%",
			"24":"0.72%"
		}
	},
	"主场球队":{
		"球队名称":"浙江毅腾",
		"防守热区":{
			"1":"1.64%",
			"2":"1.64%",
			"3":"1.64%",
			"4":"4.92%",
			"5":"1.64%",
			"6":"0.0%",
			"7":"13.11%",
			"8":"6.56%",
			"9":"13.11%",
			"10":"3.28%",
			"11":"0.0%",
			"12":"0.0%",
			"13":"11.48%",
			"14":"14.75%",
			"15":"6.56%",
			"16":"4.92%",
			"17":"0.0%",
			"18":"0.0%",
			"19":"3.28%",
			"20":"4.92%",
			"21":"4.92%",
			"22":"1.64%",
			"23":"0.0%",
			"24":"0.0%"
		},
		"进攻热区":{
			"1":"0.0%",
			"2":"4.08%",
			"3":"2.04%",
			"4":"6.12%",
			"5":"8.16%",
			"6":"10.2%",
			"7":"2.04%",
			"8":"6.12%",
			"9":"6.12%",
			"10":"2.04%",
			"11":"4.08%",
			"12":"0.0%",
			"13":"0.0%",
			"14":"6.12%",
			"15":"4.08%",
			"16":"6.12%",
			"17":"8.16%",
			"18":"2.04%",
			"19":"4.08%",
			"20":"0.0%",
			"21":"0.0%",
			"22":"4.08%",
			"23":"6.12%",
			"24":"8.16%"
		},
		"综合热区":{
			"1":"1.48%",
			"2":"3.69%",
			"3":"6.9%",
			"4":"5.91%",
			"5":"1.97%",
			"6":"0.74%",
			"7":"6.9%",
			"8":"6.4%",
			"9":"8.13%",
			"10":"4.43%",
			"11":"3.45%",
			"12":"0.99%",
			"13":"5.42%",
			"14":"7.88%",
			"15":"6.65%",
			"16":"4.93%",
			"17":"2.46%",
			"18":"1.97%",
			"19":"0.99%",
			"20":"5.67%",
			"21":"5.67%",
			"22":"4.43%",
			"23":"2.71%",
			"24":"0.25%"
		}
	}
}