{
	"主场数据":{
		"数据":{
			"射门之前的传球":19,
			"助攻":0
		},
		"一次触球后传球":{
			"总计":146,
			"成功率":"61.64%",
			"成功":90
		},
		"球队名称":"浙江毅腾",
		"传球":{
			"总计":303,
			"成功率":"67.99%",
			"成功":206
		},
		"直塞球":{
			"总计":4,
			"成功率":"25.0%",
			"成功":1
		},
		"禁区":{
			"中央成功":123,
			"防守成功率":"60.94%",
			"中央成功率":"72.35%",
			"进攻区域":69,
			"防守成功":39,
			"进攻成功率":"63.77%",
			"进攻成功":44,
			"防守区域":64,
			"中央区域":170
		},
		"距离":{
			"短传成功":103,
			"长传成功":28,
			"短传0-15m总计":141,
			"传球成功率":"72.82%",
			"长传成功率":"47.46%",
			"传球15-30m总计":103,
			"长传30m-总计":59,
			"传球成功":75,
			"短传成功率":"73.05%"
		}
	},
	"客场数据":{
		"数据":{
			"射门之前的传球":6,
			"助攻":1
		},
		"一次触球后传球":{
			"总计":164,
			"成功率":"62.8%",
			"成功":103
		},
		"球队名称":"北京北控燕京",
		"传球":{
			"总计":343,
			"成功率":"65.89%",
			"成功":226
		},
		"直塞球":{
			"总计":6,
			"成功率":"50.0%",
			"成功":3
		},
		"禁区":{
			"中央成功":147,
			"防守成功率":"56.34%",
			"中央成功率":"73.5%",
			"进攻区域":72,
			"防守成功":40,
			"进攻成功率":"54.17%",
			"进攻成功":39,
			"防守区域":71,
			"中央区域":200
		},
		"距离":{
			"短传成功":132,
			"长传成功":15,
			"短传0-15m总计":176,
			"传球成功率":"67.52%",
			"长传成功率":"30.0%",
			"传球15-30m总计":117,
			"长传30m-总计":50,
			"传球成功":79,
			"短传成功率":"75.0%"
		}
	}
}