{
    "比分": "1:0",
    "日期": "2016/7/2",
    "分组": "11轮",
    "主场球队": {
        "球队名称": "火车头青建圆方",
        "首发名单": {
            "27": "SUN Qibin",
            "13": "MA Hongwei",
            "24": "LI Boyang",
            "15": "ZHANG Bo",
            "29": "PANG Lei",
            "16": "LI Zhi",
            "10": "ZHAO Haichao",
            "12": "NIU Xiucheng",
            "8": "LI Wenxin",
            "11": "HU Mingtian",
            "9": "WANG Erzhuo"
        },
        "替补名单": {
            "7": "CHEN Huifeng",
            "20": "YANG Quan"
                    },
        "射门": 17,
        "射正": 6,
        "射正比率": "35%",
        "控球率": "54%",
        "禁区": 11,
        "30米内": 24,
        "传球": 355,
        "传球成功率": "80%",
        "直塞球": 8,
        "传中": 8,
        "传中成功率": "38%",
        "突破": 10,
        "抢断": 21,
        "犯规": 16,
        "黄": 2,
        "红": 0,
        "得分情况": {
            "分数范围": [
                "15'",
                "30'",
                "45'",
                "60'",
                "75'",
                "90'"
            ],
            "控球率": [
                58.4,
                61.7,
                44.8,
                54.8,
                58.3,
                49.2
            ],
            "射门": [
                3,
                4,
                2,
                4,
                3,
                1
            ],
            "禁区": [
                1,
                2,
                2,
                3,
                2,
                1
            ],
            "进攻30码": [
                6,
                5,
                3,
                6,
                1,
                3
            ]
        }
    },
    "客场球队": {
        "球队名称": "江苏盐城鼎力",
        "首发名单": {
            "1": "ZHAO Yanming",
            "27": "HAN Cai",
            "18": "YANG Fan",
            "5": "WANG Zhi",
            "25": "CAO Xiaodong",
            "4": "FANG Wensheng",
            "16": "GONG Hankui",
            "9": "YANG Wanshun",
            "6": "XU Zheming",
            "19": "LI Chao",
            "7": "DONG Xiang"
        },
        "替补名单": {
            "17": "XIAO Jiajie",
            "8": "WANG Peng",
            "29": "LU Shuai"
        },
        "射门": 9,
        "射正": 0,
        "射正比率": "0%",
        "控球率": "46%",
        "禁区": 5,
        "30米内": 26,
        "传球": 245,
        "传球成功率": "73%",
        "直塞球": 4,
        "传中": 12,
        "传中成功率": "17%",
        "突破": 5,
        "抢断": 16,
        "犯规": 22,
        "黄": 3,
        "红": 1,
        "得分情况": {
            "分数范围": [
                "15'",
                "30'",
                "45'",
                "60'",
                "75'",
                "90'"
            ],
            "控球率": [
                41.6,
                38.3,
                55.2,
                45.2,
                41.7,
                50.8
            ],
            "射门": [
                1,
                1,
                1,
                2,
                1,
                3
            ],
            "禁区": [
                0,
                1,
                0,
                0,
                1,
                3
            ],
            "进攻30码": [
                2,
                3,
                3,
                5,
                4,
                9
            ]
        }
    }
}
