{
    "主场数据": {
        "球队名称": "辽宁宏运",
        "抢断":{
            "总计":23,
            "成功":17,
            "成功率":73.9,
            "抢断线(m)":33.2,
            "进攻区域":1,
            "进攻成功":1,
            "进攻成功率":100.0,
            "中央区域":8,
            "中央成功":4,
            "中央成功率":50.0,
            "防守区域":14,
            "防守成功":12,
            "防守成功率":85.7
        },
        "防守":{
            "解围":40,
            "封堵":19,
            "射门封堵":1,
            "传中封堵":2,
            "拦截":2
        },
        "争抢球权":{
            "总计":34,
            "进攻区域":8,
            "中央区域":11,
            "防守区域":15,
            "犯规":20,
            "被侵犯":11,
            "越位":0
        },
        "空中争抢":{
            "进攻区域":3,
            "进攻胜利":2,
            "进攻胜率":66.7,
            "中央区域":9,
            "中央胜利":7,
            "中央胜率":77.8,
            "防守区域":6,
            "防守胜利":1,
            "防守胜率":16.7
        },
        "得分情况":{
            "范围":["15'","30'","45'","60'","75'","90'"],
            "抢断":[8,2,0,5,2,6],
            "犯规":[4,3,4,2,4,3],
            "30m内":[7,7,6,6,6,13],
            "禁区":[2,2,0,3,3,1],
            "射门":[1,1,0,0,2,4]
        }
    },
    "客场数据": {
        "球队名称": "石家庄永昌",
        "抢断":{
            "总计":16,
            "成功":14,
            "成功率":87.5,
            "抢断线(m)":39.9,
            "进攻区域":3,
            "进攻成功":3,
            "进攻成功率":100,
            "中央区域":5,
            "中央成功":5,
            "中央成功率":100.0,
            "防守区域":8,
            "防守成功":6,
            "防守成功率":75.0
        },
        "防守":{
            "解围":34,
            "封堵":20,
            "射门封堵":2,
            "传中封堵":1,
            "拦截":2
        },
        "争抢球权":{
            "总计":51,
            "进攻区域":16,
            "中央区域":21,
            "防守区域":14,
            "犯规":13,
            "被侵犯":19,
            "越位":1
        },
        "空中争抢":{
            "进攻区域":6,
            "进攻胜利":5,
            "进攻胜率":83.3,
            "中央区域":9,
            "中央胜利":2,
            "中央胜率":22.2,
            "防守区域":3,
            "防守胜利":1,
            "防守胜率":33.3
        },
        "得分情况":{
            "范围":["15'","30'","45'","60'","75'","90'"],
            "抢断":[4,1,4,2,2,3],
            "犯规":[1,2,2,5,2,1],
            "30m内":[9,8,2,4,10,5],
            "禁区":[1,3,1,0,3,2],
            "射门":[2,1,0,1,6,2]
        }
    }
}