{
	"中间对比":{
		"禁区外":{
			"进球":[
				"0",
				"0"
			],
			"射正率%":[
				"20.0%",
				"25.0%"
			],
			"射门":[
				"5",
				"4"
			],
			"射门成功率%":[
				"0.0%",
				"0.0%"
			],
			"射正":[
				"1",
				"1"
			]
		},
		"数据":{
			"射偏率%":[
				"37.5%",
				"25.0%"
			],
			"射偏":[
				"6",
				"2"
			],
			"进球数":[
				"3",
				"1"
			],
			"封堵":[
				"3",
				"2"
			],
			"射正率%":[
				"43.75%",
				"50.0%"
			],
			"一次触球射门":[
				"5",
				"2"
			],
			"射门":[
				"16",
				"8"
			],
			"射门成功率":[
				"18.75%",
				"12.5%"
			],
			"一次触球射门成功率%":[
				"31.25%",
				"25.0%"
			],
			"射正":[
				"7",
				"4"
			]
		},
		"点球":{
			"进球":[
				"0",
				"0"
			],
			"射门":[
				"0",
				"0"
			],
			"射正":[
				"0",
				"0"
			]
		},
		"禁区内":{
			"进球":[
				"3",
				"1"
			],
			"射正率%":[
				"50.0%",
				"75.0%"
			],
			"射门":[
				"10",
				"4"
			],
			"射门成功率%":[
				"30.0%",
				"25.0%"
			],
			"射正":[
				"5",
				"3"
			]
		},
		"任意球 & 角球":{
			"进球":[
				"0",
				"0"
			],
			"射门":[
				"1",
				"0"
			],
			"射正":[
				"1",
				"0"
			]
		}
	},
	"主场数据":{
		"射门类型":{
			"其他":1,
			"争抢球权":1,
			"短传":6,
			"定位球":6,
			"直塞球":0,
			"长传":0,
			"传中":0,
			"突破":2
		},
		"球队名称":"上海申鑫",
		"射门":{
			"OnTarget":[
				"17.83:75.17",
				"39.83:95.17",
				"25.50:73.50",
				"38.17:94.00"
			],
			"Other":[
				"50.50:93.17",
				"31.83:99.17",
				"31.33:92.17",
				"14.83:87.17",
				"33.33:81.33",
				"28.83:86.83",
				"16.83:94.17",
				"30.00:79.33",
				"42.33:90.17"
			],
			"Goal":[
				"33.67:89.67",
				"53.33:91.33",
				"33.67:103.33"
			]
		}
	},
	"客场数据":{
		"射门类型":{
			"其他":0,
			"争抢球权":1,
			"短传":2,
			"定位球":3,
			"直塞球":0,
			"长传":0,
			"传中":2,
			"突破":0
		},
		"球队名称":"天津权健",
		"射门":{
			"OnTarget":[
				"31.83:97.67",
				"31.17:93.17",
				"38.67:82.50"
			],
			"Other":[
				"48.83:83.00",
				"15.33:92.83",
				"20.67:81.33",
				"31.50:81.00"
			],
			"Goal":[
				"32.33:94.00"
			]
		}
	}
}